snappi_ixnetwork/__init__.py
snappi_ixnetwork/capture.py
snappi_ixnetwork/configurebgp.py
snappi_ixnetwork/customfield.py
snappi_ixnetwork/events.py
snappi_ixnetwork/exceptions.py
snappi_ixnetwork/ixnetworkconfig.py
snappi_ixnetwork/lag.py
snappi_ixnetwork/logger.py
snappi_ixnetwork/objectdb.py
snappi_ixnetwork/ping.py
snappi_ixnetwork/protocolmetrics.py
snappi_ixnetwork/resourcegroup.py
snappi_ixnetwork/serdes.py
snappi_ixnetwork/snappi_api.py
snappi_ixnetwork/timer.py
snappi_ixnetwork/trafficitem.py
snappi_ixnetwork/validation.py
snappi_ixnetwork/vport.py
snappi_ixnetwork/device/__init__.py
snappi_ixnetwork/device/base.py
snappi_ixnetwork/device/bgp.py
snappi_ixnetwork/device/bgpevpn.py
snappi_ixnetwork/device/compactor.py
snappi_ixnetwork/device/createixnconfig.py
snappi_ixnetwork/device/interface.py
snappi_ixnetwork/device/isis.py
snappi_ixnetwork/device/loopbackint.py
snappi_ixnetwork/device/macsec.py
snappi_ixnetwork/device/mka.py
snappi_ixnetwork/device/ngpf.py
snappi_ixnetwork/device/rocev2.py
snappi_ixnetwork/device/utils.py
snappi_ixnetwork/device/vxlan.py
snappi_ixnetwork-1.43.0.dist-info/METADATA
snappi_ixnetwork-1.43.0.dist-info/WHEEL
snappi_ixnetwork-1.43.0.dist-info/top_level.txt
snappi_ixnetwork-1.43.0.dist-info/RECORD
