Metadata-Version: 2.4
Name: snappi_ixnetwork
Version: 1.43.0
Summary: The Snappi IxNetwork Open Traffic Generator Python Package
Author-email: Keysight Technologies <andy.balogh@keysight.com>
License-Expression: MIT
Project-URL: Repository, https://github.com/open-traffic-generator/snappi-ixnetwork
Keywords: snappi,ixnetwork,testing,open traffic generator,automation
Classifier: Development Status :: 5 - Production/Stable
Classifier: Intended Audience :: Developers
Classifier: Topic :: Software Development :: Testing :: Traffic Generation
Classifier: Programming Language :: Python :: 3
Classifier: Programming Language :: Python :: 3.7
Classifier: Programming Language :: Python :: 3.8
Classifier: Programming Language :: Python :: 3.9
Classifier: Programming Language :: Python :: 3.10
Classifier: Programming Language :: Python :: 3.11
Classifier: Programming Language :: Python :: 3.12
Requires-Python: <4,>=3.7
Requires-Dist: ipaddr==2.2.0
Requires-Dist: netaddr==0.8.0
Requires-Dist: ipaddress==1.0.23
Requires-Dist: flake8
Requires-Dist: dpkt
Requires-Dist: black
Requires-Dist: pytest-cov
Requires-Dist: allure-pytest; python_version > "3.6"
Requires-Dist: ixnetwork-restpy>=1.7.0
Requires-Dist: build
Provides-Extra: testing
Requires-Dist: snappi==1.43.0; extra == "testing"
Requires-Dist: pytest; extra == "testing"
Requires-Dist: mock; extra == "testing"
Requires-Dist: dpkt==1.9.4; extra == "testing"
